imf_reader/__init__.py
imf_reader/config.py
imf_reader/sdr/__init__.py
imf_reader/sdr/clear_cache.py
imf_reader/sdr/read_announcements.py
imf_reader/sdr/read_exchange_rate.py
imf_reader/sdr/read_interest_rate.py
imf_reader/utils.py
imf_reader/weo/__init__.py
imf_reader/weo/api.py
imf_reader/weo/parser.py
imf_reader/weo/reader.py
imf_reader/weo/scraper.py
imf_reader-1.4.1.dist-info/WHEEL
imf_reader-1.4.1.dist-info/METADATA
imf_reader-1.4.1.dist-info/RECORD
