Metadata-Version: 2.3
Name: imf-reader
Version: 1.4.1
Summary: A package to access imf data
Author: The ONE Campaign
License: MIT
Requires-Dist: pandas>=2.2.2
Requires-Dist: requests>=2.32.1
Requires-Dist: chardet>=5.2.0
Requires-Dist: beautifulsoup4>=4.12.3
Requires-Dist: diskcache>=5.6.0
Requires-Dist: pytest>=8.2.0 ; extra == 'dev'
Requires-Dist: black>=24.4.2 ; extra == 'dev'
Requires-Dist: sphinx>=7.3.7 ; extra == 'dev'
Requires-Dist: myst-nb>=1.1.0 ; extra == 'dev'
Requires-Dist: autoapi>=2.0.1 ; extra == 'dev'
Requires-Dist: sphinx-autoapi>=3.0.0 ; extra == 'dev'
Requires-Dist: sphinx-rtd-theme>=2.0.0 ; extra == 'dev'
Requires-Dist: pytest-cov>=5.0.0 ; extra == 'dev'
Requires-Python: >=3.10
Provides-Extra: dev
